{"trial_id": "2e62c0440e80f5ee2f2c457455ef18bb", "hyperparameters": {"space": [{"class_name": "Boolean", "config": {"name": "structured_data_block_1/normalize", "default": false, "conditions": []}}, {"class_name": "Boolean", "config": {"name": "structured_data_block_1/dense_block_1/use_batchnorm", "default": false, "conditions": []}}, {"class_name": "Choice", "config": {"name": "structured_data_block_1/dense_block_1/num_layers", "default": 2, "conditions": [], "values": [1, 2, 3], "ordered": true}}, {"class_name": "Choice", "config": {"name": "structured_data_block_1/dense_block_1/units_0", "default": 32, "conditions": [], "values": [16, 32, 64, 128, 256, 512, 1024], "ordered": true}}, {"class_name": "Choice", "config": {"name": "structured_data_block_1/dense_block_1/dropout", "default": 0.0, "conditions": [], "values": [0.0, 0.25, 0.5], "ordered": true}}, {"class_name": "Choice", "config": {"name": "structured_data_block_1/dense_block_1/units_1", "default": 32, "conditions": [], "values": [16, 32, 64, 128, 256, 512, 1024], "ordered": true}}, {"class_name": "Choice", "config": {"name": "classification_head_1/dropout", "default": 0, "conditions": [], "values": [0.0, 0.25, 0.5], "ordered": true}}, {"class_name": "Choice", "config": {"name": "optimizer", "default": "adam", "conditions": [], "values": ["adam", "sgd", "adam_weight_decay"], "ordered": false}}, {"class_name": "Choice", "config": {"name": "learning_rate", "default": 0.001, "conditions": [], "values": [0.1, 0.01, 0.001, 0.0001, 2e-05, 1e-05], "ordered": true}}], "values": {"structured_data_block_1/normalize": true, "structured_data_block_1/dense_block_1/use_batchnorm": false, "structured_data_block_1/dense_block_1/num_layers": 2, "structured_data_block_1/dense_block_1/units_0": 32, "structured_data_block_1/dense_block_1/dropout": 0.5, "structured_data_block_1/dense_block_1/units_1": 32, "classification_head_1/dropout": 0.5, "optimizer": "adam", "learning_rate": 0.001}}, "metrics": {"metrics": {"loss": {"direction": "min", "observations": [{"value": [0.7909173965454102], "step": 0}, {"value": [0.7685725688934326], "step": 1}, {"value": [0.719031035900116], "step": 2}, {"value": [0.6844082474708557], "step": 3}, {"value": [0.6869717836380005], "step": 4}, {"value": [0.6723421812057495], "step": 5}, {"value": [0.6568110585212708], "step": 6}, {"value": [0.6350744962692261], "step": 7}, {"value": [0.6380388140678406], "step": 8}, {"value": [0.6292002201080322], "step": 9}, {"value": [0.6253342032432556], "step": 10}, {"value": [0.6069714426994324], "step": 11}, {"value": [0.5867827534675598], "step": 12}, {"value": [0.590475857257843], "step": 13}, {"value": [0.5909435749053955], "step": 14}, {"value": [0.5758957266807556], "step": 15}, {"value": [0.580272912979126], "step": 16}, {"value": [0.5789557099342346], "step": 17}, {"value": [0.5720393061637878], "step": 18}, {"value": [0.5759788155555725], "step": 19}, {"value": [0.56666100025177], "step": 20}, {"value": [0.5676079988479614], "step": 21}, {"value": [0.5594215989112854], "step": 22}, {"value": [0.5617091655731201], "step": 23}, {"value": [0.5659000873565674], "step": 24}, {"value": [0.5651310682296753], "step": 25}, {"value": [0.550349235534668], "step": 26}, {"value": [0.5580052137374878], "step": 27}, {"value": [0.5448828935623169], "step": 28}, {"value": [0.5433974266052246], "step": 29}, {"value": [0.5453999042510986], "step": 30}, {"value": [0.538379430770874], "step": 31}, {"value": [0.5486361384391785], "step": 32}, {"value": [0.5315811634063721], "step": 33}, {"value": [0.5433794856071472], "step": 34}, {"value": [0.5477017164230347], "step": 35}, {"value": [0.5419613122940063], "step": 36}, {"value": [0.5284594297409058], "step": 37}, {"value": [0.5452464818954468], "step": 38}, {"value": [0.5397577881813049], "step": 39}, {"value": [0.5355439186096191], "step": 40}, {"value": [0.5283566117286682], "step": 41}, {"value": [0.5303531289100647], "step": 42}, {"value": [0.5286747217178345], "step": 43}, {"value": [0.5377295017242432], "step": 44}, {"value": [0.5288718342781067], "step": 45}]}, "accuracy": {"direction": "max", "observations": [{"value": [0.2083333283662796], "step": 0}, {"value": [0.1770833283662796], "step": 1}, {"value": [0.1666666716337204], "step": 2}, {"value": [0.21875], "step": 3}, {"value": [0.2048611044883728], "step": 4}, {"value": [0.2708333432674408], "step": 5}, {"value": [0.2083333283662796], "step": 6}, {"value": [0.1875], "step": 7}, {"value": [0.1875], "step": 8}, {"value": [0.1875], "step": 9}, {"value": [0.2083333283662796], "step": 10}, {"value": [0.1736111044883728], "step": 11}, {"value": [0.2673611044883728], "step": 12}, {"value": [0.2395833283662796], "step": 13}, {"value": [0.2361111044883728], "step": 14}, {"value": [0.2291666716337204], "step": 15}, {"value": [0.2152777761220932], "step": 16}, {"value": [0.2777777910232544], "step": 17}, {"value": [0.2708333432674408], "step": 18}, {"value": [0.1944444477558136], "step": 19}, {"value": [0.2361111044883728], "step": 20}, {"value": [0.2395833283662796], "step": 21}, {"value": [0.2708333432674408], "step": 22}, {"value": [0.1909722238779068], "step": 23}, {"value": [0.2222222238779068], "step": 24}, {"value": [0.2326388955116272], "step": 25}, {"value": [0.2395833283662796], "step": 26}, {"value": [0.2222222238779068], "step": 27}, {"value": [0.25], "step": 28}, {"value": [0.2534722089767456], "step": 29}, {"value": [0.2534722089767456], "step": 30}, {"value": [0.28125], "step": 31}, {"value": [0.2673611044883728], "step": 32}, {"value": [0.25], "step": 33}, {"value": [0.2395833283662796], "step": 34}, {"value": [0.2430555522441864], "step": 35}, {"value": [0.2708333432674408], "step": 36}, {"value": [0.2569444477558136], "step": 37}, {"value": [0.2291666716337204], "step": 38}, {"value": [0.2534722089767456], "step": 39}, {"value": [0.2222222238779068], "step": 40}, {"value": [0.2673611044883728], "step": 41}, {"value": [0.2465277761220932], "step": 42}, {"value": [0.2604166567325592], "step": 43}, {"value": [0.2291666716337204], "step": 44}, {"value": [0.2743055522441864], "step": 45}]}, "val_loss": {"direction": "min", "observations": [{"value": [0.7009715437889099], "step": 0}, {"value": [0.6805638074874878], "step": 1}, {"value": [0.6636099219322205], "step": 2}, {"value": [0.6487020254135132], "step": 3}, {"value": [0.6349055767059326], "step": 4}, {"value": [0.6220247149467468], "step": 5}, {"value": [0.6096316576004028], "step": 6}, {"value": [0.5990188121795654], "step": 7}, {"value": [0.5895028114318848], "step": 8}, {"value": [0.5816874504089355], "step": 9}, {"value": [0.57389897108078], "step": 10}, {"value": [0.5667641758918762], "step": 11}, {"value": [0.5593289732933044], "step": 12}, {"value": [0.5531514286994934], "step": 13}, {"value": [0.547645092010498], "step": 14}, {"value": [0.5425208210945129], "step": 15}, {"value": [0.5384001135826111], "step": 16}, {"value": [0.5345684289932251], "step": 17}, {"value": [0.5318326950073242], "step": 18}, {"value": [0.528971791267395], "step": 19}, {"value": [0.5259935259819031], "step": 20}, {"value": [0.5236959457397461], "step": 21}, {"value": [0.5214975476264954], "step": 22}, {"value": [0.5200448036193848], "step": 23}, {"value": [0.5181651711463928], "step": 24}, {"value": [0.5170671343803406], "step": 25}, {"value": [0.5163688063621521], "step": 26}, {"value": [0.5159004330635071], "step": 27}, {"value": [0.5158576369285583], "step": 28}, {"value": [0.5151886940002441], "step": 29}, {"value": [0.5145280361175537], "step": 30}, {"value": [0.513620138168335], "step": 31}, {"value": [0.5129204988479614], "step": 32}, {"value": [0.5120569467544556], "step": 33}, {"value": [0.5112038850784302], "step": 34}, {"value": [0.5110285878181458], "step": 35}, {"value": [0.5118343830108643], "step": 36}, {"value": [0.5117928385734558], "step": 37}, {"value": [0.5118076801300049], "step": 38}, {"value": [0.5118353962898254], "step": 39}, {"value": [0.5122597217559814], "step": 40}, {"value": [0.5128723382949829], "step": 41}, {"value": [0.5129742622375488], "step": 42}, {"value": [0.5128426551818848], "step": 43}, {"value": [0.512520432472229], "step": 44}, {"value": [0.512464165687561], "step": 45}]}, "val_accuracy": {"direction": "max", "observations": [{"value": [0.08571428805589676], "step": 0}, {"value": [0.08571428805589676], "step": 1}, {"value": [0.1428571492433548], "step": 2}, {"value": [0.1428571492433548], "step": 3}, {"value": [0.11428571492433548], "step": 4}, {"value": [0.1428571492433548], "step": 5}, {"value": [0.1428571492433548], "step": 6}, {"value": [0.17142857611179352], "step": 7}, {"value": [0.22857142984867096], "step": 8}, {"value": [0.20000000298023224], "step": 9}, {"value": [0.20000000298023224], "step": 10}, {"value": [0.20000000298023224], "step": 11}, {"value": [0.20000000298023224], "step": 12}, {"value": [0.20000000298023224], "step": 13}, {"value": [0.20000000298023224], "step": 14}, {"value": [0.20000000298023224], "step": 15}, {"value": [0.22857142984867096], "step": 16}, {"value": [0.22857142984867096], "step": 17}, {"value": [0.2571428716182709], "step": 18}, {"value": [0.2571428716182709], "step": 19}, {"value": [0.2857142984867096], "step": 20}, {"value": [0.2857142984867096], "step": 21}, {"value": [0.2571428716182709], "step": 22}, {"value": [0.2857142984867096], "step": 23}, {"value": [0.2571428716182709], "step": 24}, {"value": [0.2571428716182709], "step": 25}, {"value": [0.2571428716182709], "step": 26}, {"value": [0.2571428716182709], "step": 27}, {"value": [0.2571428716182709], "step": 28}, {"value": [0.22857142984867096], "step": 29}, {"value": [0.20000000298023224], "step": 30}, {"value": [0.20000000298023224], "step": 31}, {"value": [0.22857142984867096], "step": 32}, {"value": [0.22857142984867096], "step": 33}, {"value": [0.22857142984867096], "step": 34}, {"value": [0.22857142984867096], "step": 35}, {"value": [0.17142857611179352], "step": 36}, {"value": [0.1428571492433548], "step": 37}, {"value": [0.1428571492433548], "step": 38}, {"value": [0.1428571492433548], "step": 39}, {"value": [0.17142857611179352], "step": 40}, {"value": [0.1428571492433548], "step": 41}, {"value": [0.1428571492433548], "step": 42}, {"value": [0.11428571492433548], "step": 43}, {"value": [0.11428571492433548], "step": 44}, {"value": [0.08571428805589676], "step": 45}]}}}, "score": 0.2857142984867096, "best_step": 20, "status": "COMPLETED"}